contraction_net/__init__.py
contraction_net/annotation.py
contraction_net/contraction_net.py
contraction_net/data.py
contraction_net/losses.py
contraction_net/prediction.py
contraction_net/training.py
contraction_net/utils.py
sarcasm/__init__.py
sarcasm/_version.py
sarcasm/core.py
sarcasm/exceptions.py
sarcasm/export.py
sarcasm/feature_dict.py
sarcasm/ioutils.py
sarcasm/meta_data_handler.py
sarcasm/motion.py
sarcasm/plot_utils.py
sarcasm/plots.py
sarcasm/py.typed
sarcasm/structure.py
sarcasm/structure_backup.py
sarcasm/training_data_generation.py
sarcasm/type_utils.py
sarcasm/utils.py
sarcasm/models/model_ContractionNet.pt
sarcasm/models/model_sarcomeres_generalist.pt
sarcasm/models/model_z_bands_unet3d.pt
sarcasm/structure_modules/__init__.py
sarcasm/structure_modules/detection.py
sarcasm/structure_modules/domain_clustering.py
sarcasm/structure_modules/kymograph.py
sarcasm/structure_modules/loi_detection.py
sarcasm/structure_modules/myofibril_analysis.py
sarcasm/structure_modules/sarcomere_vectors.py
sarcasm/structure_modules/z_band_analysis.py
sarcasm_app/__init__.py
sarcasm_app/__main__.py
sarcasm_app/py.typed
sarcasm_app/control/__init__.py
sarcasm_app/control/application_control.py
sarcasm_app/control/batch_processing_control.py
sarcasm_app/control/chain_execution.py
sarcasm_app/control/file_selection_control.py
sarcasm_app/control/loi_analysis_control.py
sarcasm_app/control/motion_analysis_control.py
sarcasm_app/control/popup_export.py
sarcasm_app/control/structure_analysis_control.py
sarcasm_app/hooks/hook-numpy.py
sarcasm_app/hooks/hook-vispy.py
sarcasm_app/hooks/runtime_hook_matplotlib.py
sarcasm_app/hooks/runtime_hook_pytorch.py
sarcasm_app/icons/sarcasm.icns
sarcasm_app/icons/sarcasm.ico
sarcasm_app/model/__init__.py
sarcasm_app/model/parameter.py
sarcasm_app/model/parameters.py
sarcasm_app/ui-files/file_selection.ui
sarcasm_app/ui-files/parameters_batch_processing.ui
sarcasm_app/ui-files/parameters_loi_analysis.ui
sarc_asm-0.4.1.dist-info/METADATA
sarc_asm-0.4.1.dist-info/WHEEL
sarc_asm-0.4.1.dist-info/entry_points.txt
sarc_asm-0.4.1.dist-info/licenses/LICENSE
sarc_asm-0.4.1.dist-info/RECORD
