Metadata-Version: 2.4
Name: sarc-asm
Version: 0.4.1
Summary: AI-based Sarcomere Analysis Multitool for structural and functional analysis of sarcomeres in microscopy images and movies
Project-URL: Repository, https://github.com/danihae/SarcAsM
Project-URL: Documentation, https://sarcasm.readthedocs.io
Project-URL: Issues, https://github.com/danihae/SarcAsM/issues
Project-URL: Changelog, https://github.com/danihae/SarcAsM/releases
Author-email: Daniel Haertter <dani.hae@posteo.de>
License: License
License-File: LICENSE
Classifier: Development Status :: 4 - Beta
Classifier: Intended Audience :: Science/Research
Classifier: Programming Language :: Python :: 3
Classifier: Programming Language :: Python :: 3.10
Classifier: Programming Language :: Python :: 3.11
Classifier: Programming Language :: Python :: 3.12
Classifier: Programming Language :: Python :: 3.13
Classifier: Topic :: Scientific/Engineering :: Image Processing
Requires-Python: <3.14,>=3.10
Requires-Dist: bio-image-unet<2.0.0,>=1.1.2
Requires-Dist: igraph<0.12.0,>=0.11.2
Requires-Dist: matplotlib-scalebar<0.9.0,>=0.8.0
Requires-Dist: matplotlib<4.0.0,>=3.10.0
Requires-Dist: napari<0.7.0,>=0.4.18
Requires-Dist: networkx<4.0,>=3.2
Requires-Dist: numba<0.62.0,>=0.61.2
Requires-Dist: numpy>2.2
Requires-Dist: openpyxl<4.0.0,>=3.1.4
Requires-Dist: orjson<4.0.0,>=3.10.0
Requires-Dist: pandas<3.0.0,>=2.0.0
Requires-Dist: pyqt5<5.16.0,>=5.15.4
Requires-Dist: pywavelets<2.0.0,>=1.5.0
Requires-Dist: qtutils<5.0.0,>=4.0.0
Requires-Dist: scikit-image<1.0,>0.18
Requires-Dist: scikit-learn<2.0.0,>=1.0.2
Requires-Dist: tifffile>=2023.12.9
Requires-Dist: torch<3.0.0,>=2.0.0
Requires-Dist: trackpy<0.7.0,>=0.6.4
Provides-Extra: app
Requires-Dist: pyinstaller>=6.0.0; extra == 'app'
Provides-Extra: dev
Requires-Dist: notebook<8.0.0,>=7.0.0; extra == 'dev'
Requires-Dist: ruff>=0.6.0; extra == 'dev'
Provides-Extra: docs
Requires-Dist: myst-parser<3.0.0,>=2.0.0; extra == 'docs'
Requires-Dist: nbsphinx<0.10.0,>=0.9.0; extra == 'docs'
Requires-Dist: sphinx-autoapi<4.0,>=3.0; extra == 'docs'
Requires-Dist: sphinx-rtd-theme<3.0.0,>=2.0.0; extra == 'docs'
Requires-Dist: sphinx<8.0,>=7.0; extra == 'docs'
Provides-Extra: test
Requires-Dist: pytest-cov>=4.0.0; extra == 'test'
Requires-Dist: pytest-xdist>=3.0.0; extra == 'test'
Requires-Dist: pytest>=8.4.1; extra == 'test'
